LICENSE
excelerate/__init__.py
excelerate/_sheet.py
excelerate-0.1.0.dist-info/LICENSE
excelerate-0.1.0.dist-info/WHEEL
excelerate-0.1.0.dist-info/METADATA
excelerate-0.1.0.dist-info/RECORD
